energydram/__init__.py
energydram/energy_ddr.py
energydram/energy_lpddr.py
energydram/termination.py
energydram/timing.py
energydram/voltage_domain.py
energydram/tests/__init__.py
energydram/tests/test_energy_ddr.py
energydram/tests/test_energy_lpddr.py
energydram/tests/test_termination.py
energydram/tests/test_voltage_domain.py
energydram-0.4.0.dist-info/LICENSE
energydram-0.4.0.dist-info/METADATA
energydram-0.4.0.dist-info/WHEEL
energydram-0.4.0.dist-info/top_level.txt
energydram-0.4.0.dist-info/RECORD
