Metadata-Version: 2.1
Name: energydram
Version: 0.4.0
Summary: DRAM energy calculation.
Home-page: https://github.com/gaomy3832/energydram
Author: Mingyu Gao
Author-email: mgao12@stanford.edu
License: BSD 3-clause
Keywords: DRAM energy
Platform: UNKNOWN
Classifier: Development Status :: 3 - Alpha
Classifier: Intended Audience :: Developers
Classifier: Intended Audience :: Science/Research
Classifier: License :: OSI Approved :: BSD License
Classifier: Programming Language :: Python :: 2.7
Classifier: Programming Language :: Python :: 3.4
Classifier: Programming Language :: Python :: 3.5
Classifier: Programming Language :: Python :: 3.6
Classifier: Topic :: System :: Hardware
Classifier: Topic :: Utilities
Requires-Dist: numpy (>=1.8)
Requires-Dist: coverage (>=4)
Requires-Dist: pytest (>=3)
Requires-Dist: pytest-cov (>=2)
Requires-Dist: pytest-xdist (>=1)
